setup.py
duckybot/__init__.py
duckybot/core.py
duckybot.egg-info/PKG-INFO
duckybot.egg-info/SOURCES.txt
duckybot.egg-info/dependency_links.txt
duckybot.egg-info/not-zip-safe
duckybot.egg-info/top_level.txt