Metadata-Version: 1.0
Name: duckybot
Version: 0.1
Summary: A bot for automatic posting and automated data retrieving
Home-page: https://github.com/Vasilesk/duckybot
Author: Vasilii V. Bodnariuk
Author-email: i@vasilesk.ru
License: MIT
Platform: UNKNOWN
